LICENSE
README.md
setup.py
pycongress/__init__.py
pycongress/bill.py
pycongress/client.py
pycongress/congress.py
pycongress/member.py
pycongress/utils.py
pycongress.egg-info/PKG-INFO
pycongress.egg-info/SOURCES.txt
pycongress.egg-info/dependency_links.txt
pycongress.egg-info/top_level.txt