Metadata-Version: 2.1
Name: pycongress
Version: 0.0.1
Summary: Python client for Congress.gov's API
Home-page: https://github.com/hawkirk/PyCongress
Author: harrison kirk
Author-email: harrison@hawkirk.com
License: MIT
Classifier: Intended Audience :: Developers
Classifier: License :: OSI Approved :: MIT License
Classifier: Programming Language :: Python
Classifier: Natural Language :: English
Classifier: Operating System :: OS Independent
Classifier: Topic :: Software Development :: Libraries :: Python Modules
Classifier: Development Status :: 3 - Alpha
License-File: LICENSE
